fds/__init__.py
fds/sdk/__init__.py
fds/sdk/FactSetNews/__init__.py
fds/sdk/FactSetNews/api_client.py
fds/sdk/FactSetNews/configuration.py
fds/sdk/FactSetNews/exceptions.py
fds/sdk/FactSetNews/model_utils.py
fds/sdk/FactSetNews/rest.py
fds/sdk/FactSetNews/api/__init__.py
fds/sdk/FactSetNews/api/filters_api.py
fds/sdk/FactSetNews/api/headlines_api.py
fds/sdk/FactSetNews/api/views_api.py
fds/sdk/FactSetNews/apis/__init__.py
fds/sdk/FactSetNews/model/__init__.py
fds/sdk/FactSetNews/model/create_or_edit_view_body.py
fds/sdk/FactSetNews/model/create_or_edit_view_body_data.py
fds/sdk/FactSetNews/model/create_or_edit_view_tickers.py
fds/sdk/FactSetNews/model/create_view_response.py
fds/sdk/FactSetNews/model/create_view_response_data.py
fds/sdk/FactSetNews/model/criteria.py
fds/sdk/FactSetNews/model/criteria_detail.py
fds/sdk/FactSetNews/model/criteria_one_of.py
fds/sdk/FactSetNews/model/delete_view_body.py
fds/sdk/FactSetNews/model/delete_view_body_data.py
fds/sdk/FactSetNews/model/error.py
fds/sdk/FactSetNews/model/error_response_object.py
fds/sdk/FactSetNews/model/filter_categories_response.py
fds/sdk/FactSetNews/model/filter_categories_response_data.py
fds/sdk/FactSetNews/model/filter_countries_response.py
fds/sdk/FactSetNews/model/filter_countries_response_data.py
fds/sdk/FactSetNews/model/filter_regions_response.py
fds/sdk/FactSetNews/model/filter_regions_response_data.py
fds/sdk/FactSetNews/model/filter_response.py
fds/sdk/FactSetNews/model/filter_response_data.py
fds/sdk/FactSetNews/model/filter_sources_response.py
fds/sdk/FactSetNews/model/filter_sources_response_data.py
fds/sdk/FactSetNews/model/filter_topic_response.py
fds/sdk/FactSetNews/model/filter_topic_response_data.py
fds/sdk/FactSetNews/model/filter_watchlists_response.py
fds/sdk/FactSetNews/model/filter_watchlists_response_data.py
fds/sdk/FactSetNews/model/flattened_filters.py
fds/sdk/FactSetNews/model/flattened_filters_categories.py
fds/sdk/FactSetNews/model/flattened_filters_categories_object.py
fds_sdk_factsetnews-1.0.1.dist-info/licenses/LICENSE
fds_sdk_factsetnews-1.0.1.dist-info/METADATA
fds_sdk_factsetnews-1.0.1.dist-info/WHEEL
fds_sdk_factsetnews-1.0.1.dist-info/top_level.txt
fds_sdk_factsetnews-1.0.1.dist-info/RECORD
